diffusion_pytorch_lib/__init__.py
diffusion_pytorch_lib/module.py
diffusion_pytorch_lib-1.0.2.dist-info/licenses/LICENSE
diffusion_pytorch_lib-1.0.2.dist-info/METADATA
diffusion_pytorch_lib-1.0.2.dist-info/WHEEL
diffusion_pytorch_lib-1.0.2.dist-info/top_level.txt
diffusion_pytorch_lib-1.0.2.dist-info/RECORD
