Metadata-Version: 2.4
Name: diffusion-pytorch-lib
Version: 1.0.2
Summary: A flexible PyTorch implementation of a UNet-based Denoising Diffusion Probabilistic Model (DDPM) with customizable architecture and training options.
Author-email: Mehran Bazrafkan <mhrn.bzrafkn.dev@gmail.com>
License-Expression: MIT
Keywords: DDPM,UNet-based Denoising Diffusion,Denoising Diffusion Probabilistic Model,Generative AI,Image Generation,pytorch,machine learning,deep learning
Classifier: Programming Language :: Python :: 3
Classifier: Operating System :: OS Independent
Classifier: Topic :: Scientific/Engineering :: Artificial Intelligence
Classifier: Intended Audience :: Developers
Requires-Python: >=3.10
License-File: LICENSE
Requires-Dist: torch>=1.13
Requires-Dist: einops
Requires-Dist: numpy
Dynamic: license-file
